timeperiod.py
timeperiod2-20.10.0.dist-info/LICENSE
timeperiod2-20.10.0.dist-info/METADATA
timeperiod2-20.10.0.dist-info/WHEEL
timeperiod2-20.10.0.dist-info/top_level.txt
timeperiod2-20.10.0.dist-info/RECORD
