Metadata-Version: 2.1
Name: timeperiod2
Version: 20.10.0
Summary: Python module for determining if a datetime is within a time period
Home-page: https://codeberg.org/hjacobs/python-timeperiod2
Author: Henning Jacobs
Author-email: henning.jacobs@jacobs1.de
License: UNKNOWN
Keywords: timeperiod time period datetime
Platform: UNKNOWN
Classifier: Development Status :: 4 - Beta
Classifier: License :: OSI Approved :: GNU Lesser General Public License v2 or later (LGPLv2+)
Classifier: Programming Language :: Python
Classifier: Programming Language :: Python :: 3.6
Classifier: Programming Language :: Python :: 3.7
Classifier: Programming Language :: Python :: 3.8
